openml_onnx/__init__.py
openml_onnx/config.py
openml_onnx/extension.py
openml_onnx-0.0.3.dist-info/LICENSE.md
openml_onnx-0.0.3.dist-info/METADATA
openml_onnx-0.0.3.dist-info/WHEEL
openml_onnx-0.0.3.dist-info/top_level.txt
openml_onnx-0.0.3.dist-info/RECORD
