Metadata-Version: 2.1
Name: openml-onnx
Version: 0.0.3
Summary: Onnx extension for Openml python API
Home-page: http://openml.org/
Author: 
Author-email: 
Maintainer: Prabhant Singh
Maintainer-email: prabhantsingh@gmail.com
License: BSD 3-clause
Project-URL: Documentation, https://openml.github.io/openml-onnx/
Project-URL: Source Code, https://github.com/openml/openml-onnx
Platform: UNKNOWN
Classifier: Intended Audience :: Science/Research
Classifier: Intended Audience :: Developers
Classifier: License :: OSI Approved :: BSD License
Classifier: Programming Language :: Python
Classifier: Topic :: Software Development
Classifier: Topic :: Scientific/Engineering
Classifier: Operating System :: POSIX
Classifier: Operating System :: Unix
Classifier: Operating System :: MacOS
Classifier: Programming Language :: Python :: 3
Classifier: Programming Language :: Python :: 3.5
Classifier: Programming Language :: Python :: 3.6
Classifier: Programming Language :: Python :: 3.7
Requires-Python: >=3.5
Requires-Dist: openml
Requires-Dist: onnx (==1.3.0)
